calculate/__init__.py
calculate/calc.py
calculate/unit_tests.py
izzyXYZ-1.0.data/scripts/calc.py
izzyXYZ-1.0.dist-info/METADATA
izzyXYZ-1.0.dist-info/WHEEL
izzyXYZ-1.0.dist-info/top_level.txt
izzyXYZ-1.0.dist-info/RECORD
