Metadata-Version: 2.1
Name: izzyXYZ
Version: 1.0
Summary: A small example package
Home-page: https://github.com/naturalett/getting-started
Author: izzy
Author-email: izzy@example.com
License: UNKNOWN
Platform: UNKNOWN
Requires-Python: >=3.9
Requires-Dist: distribution-Final
Requires-Dist: boto3
